{
  "customers": [
    { "id": "logo", "name": "https://cdn-images-1.medium.com/v2/resize:fit:1200/1*I_2uWtYyOrZzGcCWhr2qSQ.png" },
    { "id": "middlebanner", "name": "https://static5.lenskart.com/media/uploads/18july-2-shop-by-gender-banner-women-power-eyeglass.png" },
    { "id": "carouselitem1", "name": "https://static5.lenskart.com/media/uploads/Desktop-v2-topbanner-wildgear_03072025_rat.png" },
    { "id": "carouselitem2", "name": "https://static5.lenskart.com/media/uploads/Desktop-v2-topbanner-Cherry_blossom1.jpg" },
    { "id": "carouselitem3", "name": "https://static5.lenskart.com/media/uploads/NEW_AT_LK-Shapes_27032025rat.png" },
    { "id": "smalltextlabel", "name": "" },
    { "id": "bigtextlabel", "name": "" },
    { "id": "campaign1", "name": "" },
    { "id": "campaign2", "name": "" },
    { "id": "campaign3", "name": "" },
    { "id": "ph1", "name": "" },
    { "id": "ph2", "name": "" },
    { "id": "ph3", "name": "" }
  ]

}
